thds/adls/__init__.py
thds/adls/_etag.py
thds/adls/_fork_protector.py
thds/adls/_progress.py
thds/adls/_upload.py
thds/adls/abfss.py
thds/adls/blob_meta.py
thds/adls/blobs.py
thds/adls/cached.py
thds/adls/conf.py
thds/adls/copy.py
thds/adls/dbfs.py
thds/adls/defaults.py
thds/adls/download.py
thds/adls/errors.py
thds/adls/etag.py
thds/adls/file_lock.py
thds/adls/file_properties.py
thds/adls/fqn.py
thds/adls/global_client.py
thds/adls/hashes.py
thds/adls/impl.py
thds/adls/list_fast.py
thds/adls/md5.py
thds/adls/named_roots.py
thds/adls/py.typed
thds/adls/ro_cache.py
thds/adls/sas_tokens.py
thds/adls/shared_credential.py
thds/adls/source.py
thds/adls/source_tree.py
thds/adls/upload.py
thds/adls/uri.py
thds/adls/azcopy/__init__.py
thds/adls/azcopy/download.py
thds/adls/azcopy/login.py
thds/adls/azcopy/progress.py
thds/adls/azcopy/system_resources.py
thds/adls/azcopy/upload.py
thds/adls/tools/download.py
thds/adls/tools/ls.py
thds/adls/tools/ls_fast.py
thds/adls/tools/upload.py
thds_adls-4.5.20260130200330.dist-info/METADATA
thds_adls-4.5.20260130200330.dist-info/WHEEL
thds_adls-4.5.20260130200330.dist-info/entry_points.txt
thds_adls-4.5.20260130200330.dist-info/top_level.txt
thds_adls-4.5.20260130200330.dist-info/RECORD
