Metadata-Version: 2.4
Name: thds.adls
Version: 4.5.20260130200330
Summary: ADLS tools
Author-email: Trilliant Health <info@trillianthealth.com>
License: MIT
Project-URL: Repository, https://github.com/TrilliantHealth/trilliant-data-science
Requires-Python: >=3.9
Requires-Dist: aiohttp>=3.8.1
Requires-Dist: aiostream>=0.4.5
Requires-Dist: azure-identity>=1.9
Requires-Dist: azure-storage-file-datalake>=12.6
Requires-Dist: blake3
Requires-Dist: filelock>=3.0
Requires-Dist: xxhash
Requires-Dist: thds-core
